MANIFEST.in
README.rst
setup.cfg
setup.py
django_memcachedkeys.egg-info/PKG-INFO
django_memcachedkeys.egg-info/SOURCES.txt
django_memcachedkeys.egg-info/dependency_links.txt
django_memcachedkeys.egg-info/not-zip-safe
django_memcachedkeys.egg-info/requires.txt
django_memcachedkeys.egg-info/top_level.txt
memcachedkeys/__init__.py
memcachedkeys/pkgmeta.py
tests/__init__.py
tests/test_memcachedkeys.py