Metadata-Version: 1.0
Name: django-memcachedkeys
Version: 0.1.0
Summary: Sanitize your keys, please.
Home-page: https://github.com/hzdg/django-memcachedkeys
Author: Matthew Dapena-Tretter
Author-email: m@tthewwithanm.com
License: UNKNOWN
Keywords: django-memcachedkeys
Platform: UNKNOWN
Classifier: Development Status :: 2 - Pre-Alpha
Classifier: Framework :: Django
Classifier: Intended Audience :: Developers
Classifier: License :: OSI Approved :: BSD License
Classifier: Natural Language :: English
Classifier: Programming Language :: Python :: 2
Classifier: Programming Language :: Python :: 2.6
Classifier: Programming Language :: Python :: 2.7
Classifier: Programming Language :: Python :: 3
Classifier: Programming Language :: Python :: 3.3
